ucode_sdk/__init__.py
ucode_sdk/auth.py
ucode_sdk/builders.py
ucode_sdk/clean_test.py
ucode_sdk/config.py
ucode_sdk/files.py
ucode_sdk/function.py
ucode_sdk/helper.py
ucode_sdk/items.py
ucode_sdk/models.py
ucode_sdk/response_utils.py
ucode_sdk/sdk.py
ucode_sdk-1.0.5.dist-info/licenses/LICENSE
ucode_sdk-1.0.5.dist-info/METADATA
ucode_sdk-1.0.5.dist-info/WHEEL
ucode_sdk-1.0.5.dist-info/top_level.txt
ucode_sdk-1.0.5.dist-info/RECORD
